pg/__init__.py
pg/core.py
params_guidline-0.0.3.dist-info/LICENSE
params_guidline-0.0.3.dist-info/METADATA
params_guidline-0.0.3.dist-info/WHEEL
params_guidline-0.0.3.dist-info/top_level.txt
params_guidline-0.0.3.dist-info/RECORD
