Metadata-Version: 2.1
Name: params-guidline
Version: 0.0.3
Summary: params-guidline
Home-page: https://github.com/wo7864/params_guideline
Author: wo7864
Author-email: wo78644@gmail.com
License: MIT
Platform: UNKNOWN
Classifier: Programming Language :: Python :: 3
Classifier: License :: OSI Approved :: MIT License
Classifier: Operating System :: OS Independent
License-File: LICENSE
